_kaldilm.cp311-win_amd64.pyd
_kaldilm.lib
kaldilm_core.lib
kaldilm_fst.lib
kaldilm/__init__.py
kaldilm/__main__.py
kaldilm/arpa2fst.py
kaldilm-1.15.4.dist-info/licenses/LICENSE
kaldilm-1.15.4.dist-info/METADATA
kaldilm-1.15.4.dist-info/WHEEL
kaldilm-1.15.4.dist-info/top_level.txt
kaldilm-1.15.4.dist-info/RECORD
