Metadata-Version: 2.1
Name: kaldilm
Version: 1.15.4
Home-page: https://github.com/csukuangfj/kaldilm
Author: Fangjun Kuang
Author-email: csukuangfj@gmail.com
License: Apache-2.0
Classifier: Programming Language :: C++
Classifier: Programming Language :: Python
Classifier: Topic :: Scientific/Engineering :: Artificial Intelligence
Requires-Python: >=3.8
License-File: LICENSE
